setup.py
enecostdutils/__init__.py
enecostdutils.egg-info/PKG-INFO
enecostdutils.egg-info/SOURCES.txt
enecostdutils.egg-info/dependency_links.txt
enecostdutils.egg-info/requires.txt
enecostdutils.egg-info/top_level.txt
enecostdutils/date_tools/__init__.py
enecostdutils/date_tools/std_date_tools.py
enecostdutils/date_tools/tests_std_date_tools.py
enecostdutils/db_tools/__init__.py
enecostdutils/db_tools/std_db_tools.py
enecostdutils/ebase_tools/__init__.py
enecostdutils/ebase_tools/std_ebase_tools.py