Metadata-Version: 1.0
Name: enecostdutils
Version: 0.0.3
Summary: A python package containing all the boiler plate code for Eneco-std utils.
Home-page: UNKNOWN
Author: Vincent Visser
Author-email: UNKNOWN
License: MIT
Platform: UNKNOWN
